imery/__init__.py
imery/__main__.py
imery/app.py
imery/data_bag.py
imery/decorators.py
imery/dispatcher.py
imery/lang.py
imery/logging.py
imery/plugin_manager.py
imery/result.py
imery/stringcase.py
imery/types.py
imery/backend/audio_buffer.py
imery/backend/data_tree.py
imery/backend/kernel.py
imery/backend/simple_data_tree.py
imery/backend/types.py
imery/editor/layouts/app.yaml
imery/editor/layouts/data.yaml
imery/editor/layouts/menu.yaml
imery/editor/layouts/widgets.yaml
imery/frontend/composite.py
imery/frontend/types.py
imery/frontend/widget.py
imery/frontend/widget_factory.py
imery/frontend/layouts/builtin.yaml
imery/frontend/widgets/cool_bar.py
imery/frontend/widgets/docking.py
imery/frontend/widgets/drag.py
imery/frontend/widgets/editing.py
imery/frontend/widgets/hello_imgui_main_window.py
imery/frontend/widgets/hello_imgui_widgets.py
imery/frontend/widgets/imgui_main_window.py
imery/frontend/widgets/imguizmo.py
imery/frontend/widgets/immvision.py
imery/frontend/widgets/implot.py
imery/frontend/widgets/implot3d.py
imery/frontend/widgets/knobs.py
imery/frontend/widgets/listbox.py
imery/frontend/widgets/markdown.py
imery/frontend/widgets/matplotlib.py
imery/frontend/widgets/nanovg.py
imery/frontend/widgets/node-editor.py
imery/frontend/widgets/popup.py
imery/frontend/widgets/selectable.py
imery/frontend/widgets/simple.py
imery/frontend/widgets/spinner.py
imery/frontend/widgets/table.py
imery/frontend/widgets/text-editor.py
imery/frontend/widgets/toggle.py
imery/frontend/widgets/tree_like.py
imery/plugins/filesystem/main.py
imery/plugins/soundfile/main.py
imery/plugins/waveform/main.py
imery/plugins/waveform_st/main.py
imery/demo/classic/app.yaml
imery/demo/classic/demo.yaml
imery/demo/classic/widgets.yaml
imery/demo/hello-imgui/app.yaml
imery/demo/hello-imgui/data.yaml
imery/demo/hello-imgui/hello-imgui-widgets.yaml
imery/demo/hello-imgui/widgets.yaml
imery/demo/hello-imgui-dockable-windows-simple/app.yaml
imery/demo/hello-imgui-full/app.yaml
imery-0.0.61.dist-info/METADATA
imery-0.0.61.dist-info/WHEEL
imery-0.0.61.dist-info/entry_points.txt
imery-0.0.61.dist-info/licenses/LICENSE
imery-0.0.61.dist-info/RECORD
