Metadata-Version: 2.4
Name: imery
Version: 0.0.61
Summary: Add your description here
License-File: LICENSE
Requires-Python: >=3.12
Requires-Dist: click>=8.3.0
Requires-Dist: httpx>=0.28.1
Requires-Dist: imgui-bundle>=1.92.4
Requires-Dist: matplotlib>=3.8.0
Requires-Dist: munch>=4.0.0
Requires-Dist: pillow>=11.3.0
Requires-Dist: pyyaml>=6.0.2
Provides-Extra: audio
Requires-Dist: soundfile>=0.13.1; extra == 'audio'
Provides-Extra: dev
Requires-Dist: pytest>=9.0.2; extra == 'dev'
Requires-Dist: twine>=6.2.0; extra == 'dev'
